fedora/core/__init__.py
fedora/core/engine.py
fedora/core/utilities/lib.py
fedora/core/utilities/logger.py
fedora/sge/__init__.py
fedora/sge/engine.py
fedora/sge/grammar.py
fedora/sge/logger.py
fedora/sge/parameters.py
fedora/sge/operators/__init__.py
fedora/sge/operators/mutation.py
fedora/sge/operators/recombination.py
fedora/sge/operators/selection.py
fedora/sge/utilities/__init__.py
fedora/sge/utilities/ordered_set.py
fedora/sge/utilities/protected_math.py
fedora/sge/utilities/run_info_orm.py
fedora_framework-1.0.1.dist-info/METADATA
fedora_framework-1.0.1.dist-info/WHEEL
fedora_framework-1.0.1.dist-info/licenses/LICENSE
fedora_framework-1.0.1.dist-info/RECORD
