Metadata-Version: 2.1
Name: fedora-framework
Version: 1.0.1
Summary: The Fedora framework package
Project-URL: Homepage, https://github.com/miguelrabuge/fedora
Project-URL: Bug Tracker, https://github.com/miguelrabuge/fedora/issues
Author-email: Miguel Rabuge <rabuge@dei.uc.pt>, Nuno Lourenço <naml@dei.uc.pt>
License-File: LICENSE
Classifier: License :: OSI Approved :: MIT License
Classifier: Operating System :: OS Independent
Classifier: Programming Language :: Python :: 3
Requires-Python: >=3.10
Requires-Dist: numpy>=1.23.5
Requires-Dist: pandas>=2.0.0
Requires-Dist: pyyaml>=6.0
Requires-Dist: pyyaml>=6.0.1
Requires-Dist: scikit-learn>=1.2.2
Requires-Dist: sqlalchemy>=2.0.22
Requires-Dist: tqdm>=4.65.0
